awesome/context.py
awesome/iterator.py
awesome/__init__.py
awesomelib-0.1.0.dist-info/DESCRIPTION.rst
awesomelib-0.1.0.dist-info/METADATA
awesomelib-0.1.0.dist-info/metadata.json
awesomelib-0.1.0.dist-info/RECORD
awesomelib-0.1.0.dist-info/top_level.txt
awesomelib-0.1.0.dist-info/WHEEL
