Metadata-Version: 2.0
Name: awesomelib
Version: 0.1.0
Summary: Awesome Python Utils.
Home-page: https://github.com/tmr232/awesomelib
Author: Tamir Bahar
Author-email: UNKNOWN
License: MIT
Platform: UNKNOWN
